unitycatalog/ai/dspy/__init__.py
unitycatalog/ai/dspy/toolkit.py
unitycatalog/ai/dspy/version.py
unitycatalog_dspy-0.3.0.dist-info/METADATA
unitycatalog_dspy-0.3.0.dist-info/WHEEL
unitycatalog_dspy-0.3.0.dist-info/RECORD
