Metadata-Version: 2.4
Name: unitycatalog-dspy
Version: 0.3.0
Summary: Support for Unity Catalog functions as DSPy tools
Author-email: Unity Catalog Team <unity-catalog@databricks.com>
License: Apache-2.0
Requires-Python: >=3.10
Requires-Dist: dspy>=3.0.0
Requires-Dist: pydantic<3,>=2
Requires-Dist: unitycatalog-ai
Provides-Extra: databricks
Requires-Dist: unitycatalog-ai[databricks]; extra == 'databricks'
Provides-Extra: databricks-dev
Requires-Dist: unitycatalog-ai[databricks-dev]; extra == 'databricks-dev'
Provides-Extra: dev
Requires-Dist: unitycatalog-ai[dev]; extra == 'dev'
